{
  "imDbId": "tt0056172",
  "title": "Lawrence of Arabia",
  "fullTitle": "Lawrence of Arabia (1962)",
  "type": "Movie",
  "year": "1962",
  "description": "31 wins & 15 nominations",
  "items": [
    {
      "eventTitle": "Academy Awards, USA",
      "awardEventDetails": [
        {
          "image": "https://m.media-amazon.com/images/M/MV5BZDAyNDc1MGMtMWExNi00MDBlLTk3MzYtMTAyMTk4NGM1MGNiL2ltYWdlXkEyXkFqcGdeQXVyMTc4MzI2NQ@@._V1_Ratio1.2800_AL_.jpg",
          "title": "1963 Winner Oscar",
          "for": "Best Picture",
          "description": "Sam Spiegel"
        },
        {
          "image": "https://m.media-amazon.com/images/M/MV5BMjA0MDYyNzczN15BMl5BanBnXkFtZTYwNjMzNjMz._V1_Ratio1.0000_AL_.jpg",
          "title": "1963 Nominee Oscar",
          "for": "Best Actor in a Leading Role",
          "description": "Peter O'Toole"
        },
        {
          "image": "https://m.media-amazon.com/images/M/MV5BMTU0ODg3MjM0OF5BMl5BanBnXkFtZTYwNTM2MDU0._V1_Ratio1.0000_AL_.jpg",
          "title": "1963 Nominee Oscar",
          "for": "Best Actor in a Supporting Role",
          "description": "Omar Sharif"
        },
        {
          "image": "https://m.media-amazon.com/images/M/MV5BMjM3NzIzMzg4M15BMl5BanBnXkFtZTcwOTA1Mzg3Mw@@._V1_Ratio1.0000_AL_.jpg",
          "title": "1963 Winner Oscar",
          "for": "Best Director",
          "description": "David Lean"
        },
        {
          "image": "https://m.media-amazon.com/images/M/MV5BZDliMjU1ZDUtNTgzOS00NDU5LWFhM2ItNDk0ZWU4ZDc5M2JlXkEyXkFqcGdeQXVyMTc4MzI2NQ@@._V1_Ratio1.0000_AL_.jpg",
          "title": "1963 Nominee Oscar",
          "for": "Best Writing, Screenplay Based on Material from Another Medium",
          "description": "Robert Bolt - Michael Wilson (The nomination for Wilson was granted on 26 September 1995 by the Academy Board of Directors, after research at the WGA found that the then blacklisted writer shared the screenwriting credit with Bolt.)"
        }
      ]
    },
    {
      "eventTitle": "BAFTA Awards",
      "awardEventDetails": [
        {
          "image": "https://m.media-amazon.com/images/M/MV5BMjA0MDYyNzczN15BMl5BanBnXkFtZTYwNjMzNjMz._V1_Ratio1.0000_AL_.jpg",
          "title": "1963 Winner BAFTA Film Award",
          "for": "Best British Actor",
          "description": "Peter O'Toole"
        },
        {
          "image": "https://m.media-amazon.com/images/M/MV5BYWY5ZjhjNGYtZmI2Ny00ODM0LWFkNzgtZmI1YzA2N2MxMzA0XkEyXkFqcGdeQXVyNjUwNzk3NDc@._V1_Ratio0.7027_AL_.jpg",
          "title": "1963 Winner BAFTA Film Award",
          "for": "Best British Film",
          "description": ""
        },
        {
          "image": "https://m.media-amazon.com/images/M/MV5BZDliMjU1ZDUtNTgzOS00NDU5LWFhM2ItNDk0ZWU4ZDc5M2JlXkEyXkFqcGdeQXVyMTc4MzI2NQ@@._V1_Ratio1.0000_AL_.jpg",
          "title": "1963 Winner BAFTA Film Award",
          "for": "Best British Screenplay",
          "description": "Robert Bolt"
        },
        {
          "image": "https://m.media-amazon.com/images/M/MV5BYWY5ZjhjNGYtZmI2Ny00ODM0LWFkNzgtZmI1YzA2N2MxMzA0XkEyXkFqcGdeQXVyNjUwNzk3NDc@._V1_Ratio0.7027_AL_.jpg",
          "title": "1963 Winner BAFTA Film Award",
          "for": "Best Film from any Source",
          "description": ""
        },
        {
          "image": "https://m.media-amazon.com/images/M/MV5BMTY2MTAxMzIxMV5BMl5BanBnXkFtZTYwODc3OTE2._V1_Ratio1.0000_AL_.jpg",
          "title": "1963 Nominee BAFTA Film Award",
          "for": "Best Foreign Actor",
          "description": "Anthony Quinn"
        }
      ]
    },
    {
      "eventTitle": "Online Film & Television Association",
      "awardEventDetails": [
        {
          "image": "https://m.media-amazon.com/images/M/MV5BMTQ5MDQ3MzE3OF5BMl5BanBnXkFtZTgwMzU4NDE2MDE@._V1_Ratio1.0000_AL_.jpg",
          "title": "2021 Winner OFTA Film Hall of Fame",
          "for": "Score",
          "description": "Maurice Jarre"
        },
        {
          "image": "https://m.media-amazon.com/images/M/MV5BYWY5ZjhjNGYtZmI2Ny00ODM0LWFkNzgtZmI1YzA2N2MxMzA0XkEyXkFqcGdeQXVyNjUwNzk3NDc@._V1_Ratio0.7027_AL_.jpg",
          "title": "1999 Winner OFTA Film Hall of Fame",
          "for": "Motion Picture",
          "description": ""
        }
      ]
    },
    {
      "eventTitle": "Academy of Science Fiction, Fantasy & Horror Films, USA",
      "awardEventDetails": [
        {
          "image": "https://m.media-amazon.com/images/M/MV5BYWY5ZjhjNGYtZmI2Ny00ODM0LWFkNzgtZmI1YzA2N2MxMzA0XkEyXkFqcGdeQXVyNjUwNzk3NDc@._V1_Ratio0.7027_AL_.jpg",
          "title": "2013 Nominee Saturn Award",
          "for": "Best DVD/Blu-Ray Special Edition Release",
          "description": " (For the \"50th Anniversary Collector's Edition\" release.)"
        }
      ]
    },
    {
      "eventTitle": "International Film Music Critics Award (IFMCA)",
      "awardEventDetails": [
        {
          "image": "https://m.media-amazon.com/images/M/MV5BMTQ5MDQ3MzE3OF5BMl5BanBnXkFtZTgwMzU4NDE2MDE@._V1_Ratio1.0000_AL_.jpg",
          "title": "2011 Nominee IFMCA Award",
          "for": "Best Archival Release of an Existing Score",
          "description": "Maurice Jarre (music) - Nic Raine (conductor) - James Fitzpatrick (album producer) - Frank K. DeWald (liner notes)"
        }
      ]
    },
    {
      "eventTitle": "PGA Awards",
      "awardEventDetails": [
        {
          "image": "https://m.media-amazon.com/images/M/MV5BZDAyNDc1MGMtMWExNi00MDBlLTk3MzYtMTAyMTk4NGM1MGNiL2ltYWdlXkEyXkFqcGdeQXVyMTc4MzI2NQ@@._V1_Ratio1.2800_AL_.jpg",
          "title": "2001 Winner PGA Hall of Fame - Motion Pictures",
          "for": "",
          "description": "Sam Spiegel"
        }
      ]
    },
    {
      "eventTitle": "National Film Preservation Board, USA",
      "awardEventDetails": [
        {
          "image": "https://m.media-amazon.com/images/M/MV5BYWY5ZjhjNGYtZmI2Ny00ODM0LWFkNzgtZmI1YzA2N2MxMzA0XkEyXkFqcGdeQXVyNjUwNzk3NDc@._V1_Ratio0.7027_AL_.jpg",
          "title": "1991 Winner National Film Registry",
          "for": "",
          "description": ""
        }
      ]
    },
    {
      "eventTitle": "Italian National Syndicate of Film Journalists",
      "awardEventDetails": [
        {
          "image": "https://m.media-amazon.com/images/M/MV5BMjM3NzIzMzg4M15BMl5BanBnXkFtZTcwOTA1Mzg3Mw@@._V1_Ratio1.0000_AL_.jpg",
          "title": "1964 Winner Silver Ribbon",
          "for": "Best Foreign Director (Regista del Miglior Film Straniero)",
          "description": "David Lean"
        }
      ]
    },
    {
      "eventTitle": "David di Donatello Awards",
      "awardEventDetails": [
        {
          "image": "https://m.media-amazon.com/images/M/MV5BZDAyNDc1MGMtMWExNi00MDBlLTk3MzYtMTAyMTk4NGM1MGNiL2ltYWdlXkEyXkFqcGdeQXVyMTc4MzI2NQ@@._V1_Ratio1.2800_AL_.jpg",
          "title": "1964 Winner David",
          "for": "Best Foreign Production (Migliore Produzione Straniera)",
          "description": "Sam Spiegel (producer)"
        },
        {
          "image": "https://m.media-amazon.com/images/M/MV5BMjA0MDYyNzczN15BMl5BanBnXkFtZTYwNjMzNjMz._V1_Ratio1.0000_AL_.jpg",
          "title": "1964 Winner David",
          "for": "Best Foreign Actor (Migliore Attore Straniero)",
          "description": "Peter O'Toole (Tied with Fredric March for Seven Days in May (1964).)"
        }
      ]
    },
    {
      "eventTitle": "Grammy Awards",
      "awardEventDetails": [
        {
          "image": "https://m.media-amazon.com/images/M/MV5BMTQ5MDQ3MzE3OF5BMl5BanBnXkFtZTgwMzU4NDE2MDE@._V1_Ratio1.0000_AL_.jpg",
          "title": "1964 Nominee Grammy",
          "for": "Best Original Score from a Motion Picture or Television Show",
          "description": "Maurice Jarre"
        }
      ]
    },
    {
      "eventTitle": "Kinema Junpo Awards",
      "awardEventDetails": [
        {
          "image": "https://m.media-amazon.com/images/M/MV5BMjM3NzIzMzg4M15BMl5BanBnXkFtZTcwOTA1Mzg3Mw@@._V1_Ratio1.0000_AL_.jpg",
          "title": "1964 Winner Kinema Junpo Award",
          "for": "Best Foreign Language Film",
          "description": "David Lean"
        }
      ]
    },
    {
      "eventTitle": "Golden Globes, USA",
      "awardEventDetails": [
        {
          "image": "https://m.media-amazon.com/images/M/MV5BYWY5ZjhjNGYtZmI2Ny00ODM0LWFkNzgtZmI1YzA2N2MxMzA0XkEyXkFqcGdeQXVyNjUwNzk3NDc@._V1_Ratio0.7027_AL_.jpg",
          "title": "1963 Winner Golden Globe",
          "for": "Best Motion Picture - Drama",
          "description": ""
        },
        {
          "image": "https://m.media-amazon.com/images/M/MV5BMTY2MTAxMzIxMV5BMl5BanBnXkFtZTYwODc3OTE2._V1_Ratio1.0000_AL_.jpg",
          "title": "1963 Nominee Golden Globe",
          "for": "Best Actor - Drama",
          "description": "Anthony Quinn"
        },
        {
          "image": "https://m.media-amazon.com/images/M/MV5BMjA0MDYyNzczN15BMl5BanBnXkFtZTYwNjMzNjMz._V1_Ratio1.0000_AL_.jpg",
          "title": "1963 Nominee Golden Globe",
          "for": "Best Actor - Drama",
          "description": "Peter O'Toole"
        },
        {
          "image": "https://m.media-amazon.com/images/M/MV5BMTU0ODg3MjM0OF5BMl5BanBnXkFtZTYwNTM2MDU0._V1_Ratio1.0000_AL_.jpg",
          "title": "1963 Winner Golden Globe",
          "for": "Best Supporting Actor",
          "description": "Omar Sharif"
        },
        {
          "image": "https://m.media-amazon.com/images/M/MV5BMjM3NzIzMzg4M15BMl5BanBnXkFtZTcwOTA1Mzg3Mw@@._V1_Ratio1.0000_AL_.jpg",
          "title": "1963 Winner Golden Globe",
          "for": "Best Director",
          "description": "David Lean"
        }
      ]
    },
    {
      "eventTitle": "Writers' Guild of Great Britain",
      "awardEventDetails": [
        {
          "image": "https://m.media-amazon.com/images/M/MV5BZDliMjU1ZDUtNTgzOS00NDU5LWFhM2ItNDk0ZWU4ZDc5M2JlXkEyXkFqcGdeQXVyMTc4MzI2NQ@@._V1_Ratio1.0000_AL_.jpg",
          "title": "1963 Winner Writers' Guild of Great Britain Award",
          "for": "Best British Dramatic Screenplay",
          "description": "Robert Bolt - Michael Wilson"
        }
      ]
    },
    {
      "eventTitle": "American Cinema Editors, USA",
      "awardEventDetails": [
        {
          "image": "https://m.media-amazon.com/images/M/MV5BMjYwNDUxMTQwN15BMl5BanBnXkFtZTgwOTA4OTc0NTM@._V1_Ratio1.0000_AL_.jpg",
          "title": "1963 Nominee Eddie",
          "for": "Best Edited Feature Film",
          "description": "Anne V. Coates"
        }
      ]
    },
    {
      "eventTitle": "Directors Guild of America, USA",
      "awardEventDetails": [
        {
          "image": "https://m.media-amazon.com/images/M/MV5BMjM3NzIzMzg4M15BMl5BanBnXkFtZTcwOTA1Mzg3Mw@@._V1_Ratio1.0000_AL_.jpg",
          "title": "1963 Winner DGA Award",
          "for": "Outstanding Directorial Achievement in Motion Pictures",
          "description": "David Lean - Roy Stevens (assistant director) (plaque)"
        }
      ]
    },
    {
      "eventTitle": "Laurel Awards",
      "awardEventDetails": [
        {
          "image": "https://m.media-amazon.com/images/M/MV5BYWY5ZjhjNGYtZmI2Ny00ODM0LWFkNzgtZmI1YzA2N2MxMzA0XkEyXkFqcGdeQXVyNjUwNzk3NDc@._V1_Ratio0.7027_AL_.jpg",
          "title": "1963 Winner Golden Laurel",
          "for": "Top Road Show",
          "description": ""
        },
        {
          "image": "https://m.media-amazon.com/images/M/MV5BMjA0MDYyNzczN15BMl5BanBnXkFtZTYwNjMzNjMz._V1_Ratio1.0000_AL_.jpg",
          "title": "1963 Nominee Golden Laurel",
          "for": "Top Male Dramatic Performance",
          "description": "Peter O'Toole (4th place.)"
        },
        {
          "image": "https://m.media-amazon.com/images/M/MV5BMTU0ODg3MjM0OF5BMl5BanBnXkFtZTYwNTM2MDU0._V1_Ratio1.0000_AL_.jpg",
          "title": "1963 Nominee Golden Laurel",
          "for": "Top Male Supporting Performance",
          "description": "Omar Sharif (4th place.)"
        },
        {
          "image": "https://m.media-amazon.com/images/M/MV5BMTQ5MDQ3MzE3OF5BMl5BanBnXkFtZTgwMzU4NDE2MDE@._V1_Ratio1.0000_AL_.jpg",
          "title": "1963 Nominee Golden Laurel",
          "for": "Top Song",
          "description": "Maurice Jarre (5th place. For the song \"Theme Song\".)"
        }
      ]
    },
    {
      "eventTitle": "National Board of Review, USA",
      "awardEventDetails": [
        {
          "image": "https://m.media-amazon.com/images/M/MV5BMjM3NzIzMzg4M15BMl5BanBnXkFtZTcwOTA1Mzg3Mw@@._V1_Ratio1.0000_AL_.jpg",
          "title": "1962 Winner NBR Award",
          "for": "Best Director",
          "description": "David Lean"
        },
        {
          "image": "https://m.media-amazon.com/images/M/MV5BYWY5ZjhjNGYtZmI2Ny00ODM0LWFkNzgtZmI1YzA2N2MxMzA0XkEyXkFqcGdeQXVyNjUwNzk3NDc@._V1_Ratio0.7027_AL_.jpg",
          "title": "1962 Winner NBR Award",
          "for": "Top Ten Films",
          "description": ""
        }
      ]
    },
    {
      "eventTitle": "British Society of Cinematographers",
      "awardEventDetails": [
        {
          "image": "https://m.media-amazon.com/images/M/MV5BM2JjNzE2MDMtNjQzMC00ZWYzLTkzMjgtNzExNjhmNWE2OWY3XkEyXkFqcGdeQXVyMTQxMjk0Mg@@._V1_Ratio1.2400_AL_.jpg",
          "title": "1962 Winner Best Cinematography Award",
          "for": "",
          "description": "Freddie Young"
        }
      ]
    },
    {
      "eventTitle": "Faro Island Film Festival",
      "awardEventDetails": [
        {
          "image": "https://m.media-amazon.com/images/M/MV5BMjM3NzIzMzg4M15BMl5BanBnXkFtZTcwOTA1Mzg3Mw@@._V1_Ratio1.0000_AL_.jpg",
          "title": "1962 Nominee Golden Train Award",
          "for": "Best Film",
          "description": "David Lean"
        }
      ]
    }
  ],
  "awardsHtml": "<div class=\"awards\">\r\n    <h5>31 wins & 15 nominations</h5>\r\n    <h3>Academy Awards, USA</h3>\r\n    <table>\r\n        <tbody>\r\n            <tr>\r\n                <td>\r\n                    <b>1963 Winner Oscar</b>\r\n                    <br />\r\n                    Best Picture\r\n                    <br />\r\n                    Sam Spiegel\r\n                </td>\r\n            </tr>\r\n            <tr>\r\n                <td>\r\n                    <b>1963 Nominee Oscar</b>\r\n                    <br />\r\n                    Best Actor in a Leading Role\r\n                    <br />\r\n                    Peter O'Toole\r\n                </td>\r\n            </tr>\r\n            <tr>\r\n                <td>\r\n                    <b>1963 Nominee Oscar</b>\r\n                    <br />\r\n                    Best Actor in a Supporting Role\r\n                    <br />\r\n                    Omar Sharif\r\n                </td>\r\n            </tr>\r\n            <tr>\r\n                <td>\r\n                    <b>1963 Winner Oscar</b>\r\n                    <br />\r\n                    Best Director\r\n                    <br />\r\n                    David Lean\r\n                </td>\r\n            </tr>\r\n            <tr>\r\n                <td>\r\n                    <b>1963 Nominee Oscar</b>\r\n                    <br />\r\n                    Best Writing, Screenplay Based on Material from Another Medium\r\n                    <br />\r\n                    Robert Bolt - Michael Wilson (The nomination for Wilson was granted on 26 September 1995 by the Academy Board of Directors, after research at the WGA found that the then blacklisted writer shared the screenwriting credit with Bolt.)\r\n                </td>\r\n            </tr>\r\n        </tbody>\r\n    </table>\r\n    <h3>BAFTA Awards</h3>\r\n    <table>\r\n        <tbody>\r\n            <tr>\r\n                <td>\r\n                    <b>1963 Winner BAFTA Film Award</b>\r\n                    <br />\r\n                    Best British Actor\r\n                    <br />\r\n                    Peter O'Toole\r\n                </td>\r\n            </tr>\r\n            <tr>\r\n                <td>\r\n                    <b>1963 Winner BAFTA Film Award</b>\r\n                    <br />\r\n                    Best British Film\r\n                </td>\r\n            </tr>\r\n            <tr>\r\n                <td>\r\n                    <b>1963 Winner BAFTA Film Award</b>\r\n                    <br />\r\n                    Best British Screenplay\r\n                    <br />\r\n                    Robert Bolt\r\n                </td>\r\n            </tr>\r\n            <tr>\r\n                <td>\r\n                    <b>1963 Winner BAFTA Film Award</b>\r\n                    <br />\r\n                    Best Film from any Source\r\n                </td>\r\n            </tr>\r\n            <tr>\r\n                <td>\r\n                    <b>1963 Nominee BAFTA Film Award</b>\r\n                    <br />\r\n                    Best Foreign Actor\r\n                    <br />\r\n                    Anthony Quinn\r\n                </td>\r\n            </tr>\r\n        </tbody>\r\n    </table>\r\n    <h3>Online Film & Television Association</h3>\r\n    <table>\r\n        <tbody>\r\n            <tr>\r\n                <td>\r\n                    <b>2021 Winner OFTA Film Hall of Fame</b>\r\n                    <br />\r\n                    Score\r\n                    <br />\r\n                    Maurice Jarre\r\n                </td>\r\n            </tr>\r\n            <tr>\r\n                <td>\r\n                    <b>1999 Winner OFTA Film Hall of Fame</b>\r\n                    <br />\r\n                    Motion Picture\r\n                </td>\r\n            </tr>\r\n        </tbody>\r\n    </table>\r\n    <h3>Academy of Science Fiction, Fantasy & Horror Films, USA</h3>\r\n    <table>\r\n        <tbody>\r\n            <tr>\r\n                <td>\r\n                    <b>2013 Nominee Saturn Award</b>\r\n                    <br />\r\n                    Best DVD/Blu-Ray Special Edition Release\r\n                    <br />\r\n                     (For the \"50th Anniversary Collector's Edition\" release.)\r\n                </td>\r\n            </tr>\r\n        </tbody>\r\n    </table>\r\n    <h3>International Film Music Critics Award (IFMCA)</h3>\r\n    <table>\r\n        <tbody>\r\n            <tr>\r\n                <td>\r\n                    <b>2011 Nominee IFMCA Award</b>\r\n                    <br />\r\n                    Best Archival Release of an Existing Score\r\n                    <br />\r\n                    Maurice Jarre (music) - Nic Raine (conductor) - James Fitzpatrick (album producer) - Frank K. DeWald (liner notes)\r\n                </td>\r\n            </tr>\r\n        </tbody>\r\n    </table>\r\n    <h3>PGA Awards</h3>\r\n    <table>\r\n        <tbody>\r\n            <tr>\r\n                <td>\r\n                    <b>2001 Winner PGA Hall of Fame - Motion Pictures</b>\r\n                    <br />\r\n                    Sam Spiegel\r\n                </td>\r\n            </tr>\r\n        </tbody>\r\n    </table>\r\n    <h3>National Film Preservation Board, USA</h3>\r\n    <table>\r\n        <tbody>\r\n            <tr>\r\n                <td>\r\n                    <b>1991 Winner National Film Registry</b>\r\n                </td>\r\n            </tr>\r\n        </tbody>\r\n    </table>\r\n    <h3>Italian National Syndicate of Film Journalists</h3>\r\n    <table>\r\n        <tbody>\r\n            <tr>\r\n                <td>\r\n                    <b>1964 Winner Silver Ribbon</b>\r\n                    <br />\r\n                    Best Foreign Director (Regista del Miglior Film Straniero)\r\n                    <br />\r\n                    David Lean\r\n                </td>\r\n            </tr>\r\n        </tbody>\r\n    </table>\r\n    <h3>David di Donatello Awards</h3>\r\n    <table>\r\n        <tbody>\r\n            <tr>\r\n                <td>\r\n                    <b>1964 Winner David</b>\r\n                    <br />\r\n                    Best Foreign Production (Migliore Produzione Straniera)\r\n                    <br />\r\n                    Sam Spiegel (producer)\r\n                </td>\r\n            </tr>\r\n            <tr>\r\n                <td>\r\n                    <b>1964 Winner David</b>\r\n                    <br />\r\n                    Best Foreign Actor (Migliore Attore Straniero)\r\n                    <br />\r\n                    Peter O'Toole (Tied with Fredric March for Seven Days in May (1964).)\r\n                </td>\r\n            </tr>\r\n        </tbody>\r\n    </table>\r\n    <h3>Grammy Awards</h3>\r\n    <table>\r\n        <tbody>\r\n            <tr>\r\n                <td>\r\n                    <b>1964 Nominee Grammy</b>\r\n                    <br />\r\n                    Best Original Score from a Motion Picture or Television Show\r\n                    <br />\r\n                    Maurice Jarre\r\n                </td>\r\n            </tr>\r\n        </tbody>\r\n    </table>\r\n    <h3>Kinema Junpo Awards</h3>\r\n    <table>\r\n        <tbody>\r\n            <tr>\r\n                <td>\r\n                    <b>1964 Winner Kinema Junpo Award</b>\r\n                    <br />\r\n                    Best Foreign Language Film\r\n                    <br />\r\n                    David Lean\r\n                </td>\r\n            </tr>\r\n        </tbody>\r\n    </table>\r\n    <h3>Golden Globes, USA</h3>\r\n    <table>\r\n        <tbody>\r\n            <tr>\r\n                <td>\r\n                    <b>1963 Winner Golden Globe</b>\r\n                    <br />\r\n                    Best Motion Picture - Drama\r\n                </td>\r\n            </tr>\r\n            <tr>\r\n                <td>\r\n                    <b>1963 Nominee Golden Globe</b>\r\n                    <br />\r\n                    Best Actor - Drama\r\n                    <br />\r\n                    Anthony Quinn\r\n                </td>\r\n            </tr>\r\n            <tr>\r\n                <td>\r\n                    <b>1963 Nominee Golden Globe</b>\r\n                    <br />\r\n                    Best Actor - Drama\r\n                    <br />\r\n                    Peter O'Toole\r\n                </td>\r\n            </tr>\r\n            <tr>\r\n                <td>\r\n                    <b>1963 Winner Golden Globe</b>\r\n                    <br />\r\n                    Best Supporting Actor\r\n                    <br />\r\n                    Omar Sharif\r\n                </td>\r\n            </tr>\r\n            <tr>\r\n                <td>\r\n                    <b>1963 Winner Golden Globe</b>\r\n                    <br />\r\n                    Best Director\r\n                    <br />\r\n                    David Lean\r\n                </td>\r\n            </tr>\r\n        </tbody>\r\n    </table>\r\n    <h3>Writers' Guild of Great Britain</h3>\r\n    <table>\r\n        <tbody>\r\n            <tr>\r\n                <td>\r\n                    <b>1963 Winner Writers' Guild of Great Britain Award</b>\r\n                    <br />\r\n                    Best British Dramatic Screenplay\r\n                    <br />\r\n                    Robert Bolt - Michael Wilson\r\n                </td>\r\n            </tr>\r\n        </tbody>\r\n    </table>\r\n    <h3>American Cinema Editors, USA</h3>\r\n    <table>\r\n        <tbody>\r\n            <tr>\r\n                <td>\r\n                    <b>1963 Nominee Eddie</b>\r\n                    <br />\r\n                    Best Edited Feature Film\r\n                    <br />\r\n                    Anne V. Coates\r\n                </td>\r\n            </tr>\r\n        </tbody>\r\n    </table>\r\n    <h3>Directors Guild of America, USA</h3>\r\n    <table>\r\n        <tbody>\r\n            <tr>\r\n                <td>\r\n                    <b>1963 Winner DGA Award</b>\r\n                    <br />\r\n                    Outstanding Directorial Achievement in Motion Pictures\r\n                    <br />\r\n                    David Lean - Roy Stevens (assistant director) (plaque)\r\n                </td>\r\n            </tr>\r\n        </tbody>\r\n    </table>\r\n    <h3>Laurel Awards</h3>\r\n    <table>\r\n        <tbody>\r\n            <tr>\r\n                <td>\r\n                    <b>1963 Winner Golden Laurel</b>\r\n                    <br />\r\n                    Top Road Show\r\n                </td>\r\n            </tr>\r\n            <tr>\r\n                <td>\r\n                    <b>1963 Nominee Golden Laurel</b>\r\n                    <br />\r\n                    Top Male Dramatic Performance\r\n                    <br />\r\n                    Peter O'Toole (4th place.)\r\n                </td>\r\n            </tr>\r\n            <tr>\r\n                <td>\r\n                    <b>1963 Nominee Golden Laurel</b>\r\n                    <br />\r\n                    Top Male Supporting Performance\r\n                    <br />\r\n                    Omar Sharif (4th place.)\r\n                </td>\r\n            </tr>\r\n            <tr>\r\n                <td>\r\n                    <b>1963 Nominee Golden Laurel</b>\r\n                    <br />\r\n                    Top Song\r\n                    <br />\r\n                    Maurice Jarre (5th place. For the song \"Theme Song\".)\r\n                </td>\r\n            </tr>\r\n        </tbody>\r\n    </table>\r\n    <h3>National Board of Review, USA</h3>\r\n    <table>\r\n        <tbody>\r\n            <tr>\r\n                <td>\r\n                    <b>1962 Winner NBR Award</b>\r\n                    <br />\r\n                    Best Director\r\n                    <br />\r\n                    David Lean\r\n                </td>\r\n            </tr>\r\n            <tr>\r\n                <td>\r\n                    <b>1962 Winner NBR Award</b>\r\n                    <br />\r\n                    Top Ten Films\r\n                </td>\r\n            </tr>\r\n        </tbody>\r\n    </table>\r\n    <h3>British Society of Cinematographers</h3>\r\n    <table>\r\n        <tbody>\r\n            <tr>\r\n                <td>\r\n                    <b>1962 Winner Best Cinematography Award</b>\r\n                    <br />\r\n                    Freddie Young\r\n                </td>\r\n            </tr>\r\n        </tbody>\r\n    </table>\r\n    <h3>Faro Island Film Festival</h3>\r\n    <table>\r\n        <tbody>\r\n            <tr>\r\n                <td>\r\n                    <b>1962 Nominee Golden Train Award</b>\r\n                    <br />\r\n                    Best Film\r\n                    <br />\r\n                    David Lean\r\n                </td>\r\n            </tr>\r\n        </tbody>\r\n    </table>\r\n</div>\r\n",
  "errorMessage": ""
}