{
  "imDbId": "tt0040522",
  "title": "Bicycle Thieves",
  "fullTitle": "Bicycle Thieves (1948)",
  "type": "Movie",
  "year": "1948",
  "description": "20 wins & 3 nominations",
  "items": [
    {
      "eventTitle": "Academy Awards, USA",
      "awardEventDetails": [
        {
          "image": "https://m.media-amazon.com/images/M/MV5BMDE3Yzg1MmYtYTlmMy00YzNiLWJjMzMtMGYyNzY1N2JjZjBlXkEyXkFqcGdeQXVyMTc4MzI2NQ@@._V1_Ratio1.2800_AL_.jpg",
          "title": "1950 Nominee Oscar",
          "for": "Best Writing, Screenplay",
          "description": "Cesare Zavattini"
        },
        {
          "image": "https://m.media-amazon.com/images/M/MV5BNmI1ODdjODctMDlmMC00ZWViLWI5MzYtYzRhNDdjYmM3MzFjXkEyXkFqcGdeQXVyMTMxODk2OTU@._V1_Ratio0.7027_AL_.jpg",
          "title": "1950 Winner Honorary Award",
          "for": "",
          "description": " (Italy. Voted by the Academy Board of Governors as the most outstanding foreign language film released in the United States during 1949.)"
        }
      ]
    },
    {
      "eventTitle": "BAFTA Awards",
      "awardEventDetails": [
        {
          "image": "https://m.media-amazon.com/images/M/MV5BNmI1ODdjODctMDlmMC00ZWViLWI5MzYtYzRhNDdjYmM3MzFjXkEyXkFqcGdeQXVyMTMxODk2OTU@._V1_Ratio0.7027_AL_.jpg",
          "title": "1950 Winner BAFTA Film Award",
          "for": "Best Film from any Source",
          "description": " (Italy.)"
        }
      ]
    },
    {
      "eventTitle": "Online Film & Television Association",
      "awardEventDetails": [
        {
          "image": "https://m.media-amazon.com/images/M/MV5BNmI1ODdjODctMDlmMC00ZWViLWI5MzYtYzRhNDdjYmM3MzFjXkEyXkFqcGdeQXVyMTMxODk2OTU@._V1_Ratio0.7027_AL_.jpg",
          "title": "2008 Winner OFTA Film Hall of Fame",
          "for": "Motion Picture",
          "description": ""
        }
      ]
    },
    {
      "eventTitle": "Bodil Awards",
      "awardEventDetails": [
        {
          "image": "https://m.media-amazon.com/images/M/MV5BMzcxOTgxMTY3NV5BMl5BanBnXkFtZTgwODE5OTk3MTE@._V1_Ratio1.0000_AL_.jpg",
          "title": "1951 Winner Bodil",
          "for": "Best European Film (Bedste europæiske film)",
          "description": "Vittorio De Sica (director)"
        }
      ]
    },
    {
      "eventTitle": "Cinema Writers Circle Awards, Spain",
      "awardEventDetails": [
        {
          "image": "https://m.media-amazon.com/images/M/MV5BNmI1ODdjODctMDlmMC00ZWViLWI5MzYtYzRhNDdjYmM3MzFjXkEyXkFqcGdeQXVyMTMxODk2OTU@._V1_Ratio0.7027_AL_.jpg",
          "title": "1951 Winner CEC Award",
          "for": "Best Foreign Film (Mejor Película Extranjera)",
          "description": " (Italy.)"
        }
      ]
    },
    {
      "eventTitle": "Kinema Junpo Awards",
      "awardEventDetails": [
        {
          "image": "https://m.media-amazon.com/images/M/MV5BMzcxOTgxMTY3NV5BMl5BanBnXkFtZTgwODE5OTk3MTE@._V1_Ratio1.0000_AL_.jpg",
          "title": "1951 Winner Kinema Junpo Award",
          "for": "Best Foreign Language Film",
          "description": "Vittorio De Sica"
        }
      ]
    },
    {
      "eventTitle": "Golden Globes, USA",
      "awardEventDetails": [
        {
          "image": "https://m.media-amazon.com/images/M/MV5BNmI1ODdjODctMDlmMC00ZWViLWI5MzYtYzRhNDdjYmM3MzFjXkEyXkFqcGdeQXVyMTMxODk2OTU@._V1_Ratio0.7027_AL_.jpg",
          "title": "1950 Winner Golden Globe",
          "for": "Best Foreign Film",
          "description": " (Italy)"
        }
      ]
    },
    {
      "eventTitle": "Italian National Syndicate of Film Journalists",
      "awardEventDetails": [
        {
          "image": "https://m.media-amazon.com/images/M/MV5BNmI1ODdjODctMDlmMC00ZWViLWI5MzYtYzRhNDdjYmM3MzFjXkEyXkFqcGdeQXVyMTMxODk2OTU@._V1_Ratio0.7027_AL_.jpg",
          "title": "1949 Winner Silver Ribbon",
          "for": "Best Film (Miglior Film a Soggetto)",
          "description": ""
        },
        {
          "image": "https://m.media-amazon.com/images/M/MV5BMzcxOTgxMTY3NV5BMl5BanBnXkFtZTgwODE5OTk3MTE@._V1_Ratio1.0000_AL_.jpg",
          "title": "1949 Winner Silver Ribbon",
          "for": "Best Director (Migliore Regia)",
          "description": "Vittorio De Sica"
        },
        {
          "image": "https://m.media-amazon.com/images/M/MV5BMDE3Yzg1MmYtYTlmMy00YzNiLWJjMzMtMGYyNzY1N2JjZjBlXkEyXkFqcGdeQXVyMTc4MzI2NQ@@._V1_Ratio1.2800_AL_.jpg",
          "title": "1949 Winner Silver Ribbon",
          "for": "Best Original Story (Migliore Soggetto)",
          "description": "Cesare Zavattini"
        },
        {
          "image": "https://m.media-amazon.com/images/M/MV5BMDE3Yzg1MmYtYTlmMy00YzNiLWJjMzMtMGYyNzY1N2JjZjBlXkEyXkFqcGdeQXVyMTc4MzI2NQ@@._V1_Ratio1.2800_AL_.jpg",
          "title": "1949 Winner Silver Ribbon",
          "for": "Best Screenplay (Migliore Sceneggiatura)",
          "description": "Cesare Zavattini - Vittorio De Sica - Suso Cecchi D'Amico - Oreste Biancoli - Adolfo Franci - Gerardo Guerrieri"
        },
        {
          "image": "https://imdb-api.com/images/original/nopicture.jpg",
          "title": "1949 Winner Silver Ribbon",
          "for": "Best Cinematography (Migliore Fotografia)",
          "description": "Carlo Montuori"
        }
      ]
    },
    {
      "eventTitle": "New York Film Critics Circle Awards",
      "awardEventDetails": [
        {
          "image": "https://m.media-amazon.com/images/M/MV5BNmI1ODdjODctMDlmMC00ZWViLWI5MzYtYzRhNDdjYmM3MzFjXkEyXkFqcGdeQXVyMTMxODk2OTU@._V1_Ratio0.7027_AL_.jpg",
          "title": "1949 Winner NYFCC Award",
          "for": "Best Foreign Language Film",
          "description": " (Italy.)"
        }
      ]
    },
    {
      "eventTitle": "National Board of Review, USA",
      "awardEventDetails": [
        {
          "image": "https://m.media-amazon.com/images/M/MV5BNmI1ODdjODctMDlmMC00ZWViLWI5MzYtYzRhNDdjYmM3MzFjXkEyXkFqcGdeQXVyMTMxODk2OTU@._V1_Ratio0.7027_AL_.jpg",
          "title": "1949 Winner NBR Award",
          "for": "Best Film",
          "description": " (Italy.)"
        },
        {
          "image": "https://m.media-amazon.com/images/M/MV5BMzcxOTgxMTY3NV5BMl5BanBnXkFtZTgwODE5OTk3MTE@._V1_Ratio1.0000_AL_.jpg",
          "title": "1949 Winner NBR Award",
          "for": "Best Director",
          "description": "Vittorio De Sica"
        },
        {
          "image": "https://m.media-amazon.com/images/M/MV5BNmI1ODdjODctMDlmMC00ZWViLWI5MzYtYzRhNDdjYmM3MzFjXkEyXkFqcGdeQXVyMTMxODk2OTU@._V1_Ratio0.7027_AL_.jpg",
          "title": "1949 Winner NBR Award",
          "for": "Top Ten Films",
          "description": ""
        }
      ]
    },
    {
      "eventTitle": "Locarno International Film Festival",
      "awardEventDetails": [
        {
          "image": "https://m.media-amazon.com/images/M/MV5BMzcxOTgxMTY3NV5BMl5BanBnXkFtZTgwODE5OTk3MTE@._V1_Ratio1.0000_AL_.jpg",
          "title": "1949 Winner Special Prize of the Jury",
          "for": "",
          "description": "Vittorio De Sica"
        }
      ]
    },
    {
      "eventTitle": "Faro Island Film Festival",
      "awardEventDetails": [
        {
          "image": "https://m.media-amazon.com/images/M/MV5BMzcxOTgxMTY3NV5BMl5BanBnXkFtZTgwODE5OTk3MTE@._V1_Ratio1.0000_AL_.jpg",
          "title": "1948 Nominee Golden Train Award",
          "for": "Best Film",
          "description": "Vittorio De Sica"
        },
        {
          "image": "https://m.media-amazon.com/images/M/MV5BMDE3Yzg1MmYtYTlmMy00YzNiLWJjMzMtMGYyNzY1N2JjZjBlXkEyXkFqcGdeQXVyMTc4MzI2NQ@@._V1_Ratio1.2800_AL_.jpg",
          "title": "1948 Winner Golden Train Award",
          "for": "Best Screenplay",
          "description": "Cesare Zavattini - Gerardo Guerrieri - Gherardo Gherardi - Adolfo Franci - Vittorio De Sica - Suso Cecchi D'Amico - Oreste Biancoli"
        },
        {
          "image": "https://m.media-amazon.com/images/M/MV5BMzcxOTgxMTY3NV5BMl5BanBnXkFtZTgwODE5OTk3MTE@._V1_Ratio1.0000_AL_.jpg",
          "title": "1948 Winner Humanitarian Award",
          "for": "Main Competition",
          "description": "Vittorio De Sica"
        },
        {
          "image": "https://m.media-amazon.com/images/M/MV5BMzcxOTgxMTY3NV5BMl5BanBnXkFtZTgwODE5OTk3MTE@._V1_Ratio1.0000_AL_.jpg",
          "title": "1948 Nominee Audience Award",
          "for": "Best Film",
          "description": "Vittorio De Sica"
        }
      ]
    }
  ],
  "awardsHtml": "<div class=\"awards\">\r\n    <h5>20 wins & 3 nominations</h5>\r\n    <h3>Academy Awards, USA</h3>\r\n    <table>\r\n        <tbody>\r\n            <tr>\r\n                <td>\r\n                    <b>1950 Nominee Oscar</b>\r\n                    <br />\r\n                    Best Writing, Screenplay\r\n                    <br />\r\n                    Cesare Zavattini\r\n                </td>\r\n            </tr>\r\n            <tr>\r\n                <td>\r\n                    <b>1950 Winner Honorary Award</b>\r\n                    <br />\r\n                     (Italy. Voted by the Academy Board of Governors as the most outstanding foreign language film released in the United States during 1949.)\r\n                </td>\r\n            </tr>\r\n        </tbody>\r\n    </table>\r\n    <h3>BAFTA Awards</h3>\r\n    <table>\r\n        <tbody>\r\n            <tr>\r\n                <td>\r\n                    <b>1950 Winner BAFTA Film Award</b>\r\n                    <br />\r\n                    Best Film from any Source\r\n                    <br />\r\n                     (Italy.)\r\n                </td>\r\n            </tr>\r\n        </tbody>\r\n    </table>\r\n    <h3>Online Film & Television Association</h3>\r\n    <table>\r\n        <tbody>\r\n            <tr>\r\n                <td>\r\n                    <b>2008 Winner OFTA Film Hall of Fame</b>\r\n                    <br />\r\n                    Motion Picture\r\n                </td>\r\n            </tr>\r\n        </tbody>\r\n    </table>\r\n    <h3>Bodil Awards</h3>\r\n    <table>\r\n        <tbody>\r\n            <tr>\r\n                <td>\r\n                    <b>1951 Winner Bodil</b>\r\n                    <br />\r\n                    Best European Film (Bedste europæiske film)\r\n                    <br />\r\n                    Vittorio De Sica (director)\r\n                </td>\r\n            </tr>\r\n        </tbody>\r\n    </table>\r\n    <h3>Cinema Writers Circle Awards, Spain</h3>\r\n    <table>\r\n        <tbody>\r\n            <tr>\r\n                <td>\r\n                    <b>1951 Winner CEC Award</b>\r\n                    <br />\r\n                    Best Foreign Film (Mejor Película Extranjera)\r\n                    <br />\r\n                     (Italy.)\r\n                </td>\r\n            </tr>\r\n        </tbody>\r\n    </table>\r\n    <h3>Kinema Junpo Awards</h3>\r\n    <table>\r\n        <tbody>\r\n            <tr>\r\n                <td>\r\n                    <b>1951 Winner Kinema Junpo Award</b>\r\n                    <br />\r\n                    Best Foreign Language Film\r\n                    <br />\r\n                    Vittorio De Sica\r\n                </td>\r\n            </tr>\r\n        </tbody>\r\n    </table>\r\n    <h3>Golden Globes, USA</h3>\r\n    <table>\r\n        <tbody>\r\n            <tr>\r\n                <td>\r\n                    <b>1950 Winner Golden Globe</b>\r\n                    <br />\r\n                    Best Foreign Film\r\n                    <br />\r\n                     (Italy)\r\n                </td>\r\n            </tr>\r\n        </tbody>\r\n    </table>\r\n    <h3>Italian National Syndicate of Film Journalists</h3>\r\n    <table>\r\n        <tbody>\r\n            <tr>\r\n                <td>\r\n                    <b>1949 Winner Silver Ribbon</b>\r\n                    <br />\r\n                    Best Film (Miglior Film a Soggetto)\r\n                </td>\r\n            </tr>\r\n            <tr>\r\n                <td>\r\n                    <b>1949 Winner Silver Ribbon</b>\r\n                    <br />\r\n                    Best Director (Migliore Regia)\r\n                    <br />\r\n                    Vittorio De Sica\r\n                </td>\r\n            </tr>\r\n            <tr>\r\n                <td>\r\n                    <b>1949 Winner Silver Ribbon</b>\r\n                    <br />\r\n                    Best Original Story (Migliore Soggetto)\r\n                    <br />\r\n                    Cesare Zavattini\r\n                </td>\r\n            </tr>\r\n            <tr>\r\n                <td>\r\n                    <b>1949 Winner Silver Ribbon</b>\r\n                    <br />\r\n                    Best Screenplay (Migliore Sceneggiatura)\r\n                    <br />\r\n                    Cesare Zavattini - Vittorio De Sica - Suso Cecchi D'Amico - Oreste Biancoli - Adolfo Franci - Gerardo Guerrieri\r\n                </td>\r\n            </tr>\r\n            <tr>\r\n                <td>\r\n                    <b>1949 Winner Silver Ribbon</b>\r\n                    <br />\r\n                    Best Cinematography (Migliore Fotografia)\r\n                    <br />\r\n                    Carlo Montuori\r\n                </td>\r\n            </tr>\r\n        </tbody>\r\n    </table>\r\n    <h3>New York Film Critics Circle Awards</h3>\r\n    <table>\r\n        <tbody>\r\n            <tr>\r\n                <td>\r\n                    <b>1949 Winner NYFCC Award</b>\r\n                    <br />\r\n                    Best Foreign Language Film\r\n                    <br />\r\n                     (Italy.)\r\n                </td>\r\n            </tr>\r\n        </tbody>\r\n    </table>\r\n    <h3>National Board of Review, USA</h3>\r\n    <table>\r\n        <tbody>\r\n            <tr>\r\n                <td>\r\n                    <b>1949 Winner NBR Award</b>\r\n                    <br />\r\n                    Best Film\r\n                    <br />\r\n                     (Italy.)\r\n                </td>\r\n            </tr>\r\n            <tr>\r\n                <td>\r\n                    <b>1949 Winner NBR Award</b>\r\n                    <br />\r\n                    Best Director\r\n                    <br />\r\n                    Vittorio De Sica\r\n                </td>\r\n            </tr>\r\n            <tr>\r\n                <td>\r\n                    <b>1949 Winner NBR Award</b>\r\n                    <br />\r\n                    Top Ten Films\r\n                </td>\r\n            </tr>\r\n        </tbody>\r\n    </table>\r\n    <h3>Locarno International Film Festival</h3>\r\n    <table>\r\n        <tbody>\r\n            <tr>\r\n                <td>\r\n                    <b>1949 Winner Special Prize of the Jury</b>\r\n                    <br />\r\n                    Vittorio De Sica\r\n                </td>\r\n            </tr>\r\n        </tbody>\r\n    </table>\r\n    <h3>Faro Island Film Festival</h3>\r\n    <table>\r\n        <tbody>\r\n            <tr>\r\n                <td>\r\n                    <b>1948 Nominee Golden Train Award</b>\r\n                    <br />\r\n                    Best Film\r\n                    <br />\r\n                    Vittorio De Sica\r\n                </td>\r\n            </tr>\r\n            <tr>\r\n                <td>\r\n                    <b>1948 Winner Golden Train Award</b>\r\n                    <br />\r\n                    Best Screenplay\r\n                    <br />\r\n                    Cesare Zavattini - Gerardo Guerrieri - Gherardo Gherardi - Adolfo Franci - Vittorio De Sica - Suso Cecchi D'Amico - Oreste Biancoli\r\n                </td>\r\n            </tr>\r\n            <tr>\r\n                <td>\r\n                    <b>1948 Winner Humanitarian Award</b>\r\n                    <br />\r\n                    Main Competition\r\n                    <br />\r\n                    Vittorio De Sica\r\n                </td>\r\n            </tr>\r\n            <tr>\r\n                <td>\r\n                    <b>1948 Nominee Audience Award</b>\r\n                    <br />\r\n                    Best Film\r\n                    <br />\r\n                    Vittorio De Sica\r\n                </td>\r\n            </tr>\r\n        </tbody>\r\n    </table>\r\n</div>\r\n",
  "errorMessage": ""
}