{
  "id": "tt0036868",
  "title": "The Best Years of Our Lives",
  "originalTitle": "",
  "fullTitle": "The Best Years of Our Lives (1946)",
  "type": "Movie",
  "year": "1946",
  "image": "https://m.media-amazon.com/images/M/MV5BY2RmNTRjYzctODI4Ni00MzQyLWEyNTAtNjU0N2JkMTNhNjJkXkEyXkFqcGdeQXVyNjU0OTQ0OTY@._V1_Ratio0.6762_AL_.jpg",
  "releaseDate": "1947-05-29",
  "runtimeMins": "170",
  "runtimeStr": "2h 50min",
  "plot": "Three World War II veterans, two of them traumatized or disabled, return home to the American midwest to discover that they and their families have been irreparably changed.",
  "plotLocal": "",
  "plotLocalIsRtl": false,
  "awards": "Top rated movie #226 | Won 7 Oscars, 21 wins & 4 nominations total",
  "directors": "William Wyler",
  "directorList": [
    {
      "id": "nm0943758",
      "name": "William Wyler"
    }
  ],
  "writers": "Robert E. Sherwood, MacKinlay Kantor",
  "writerList": [
    {
      "id": "nm0792845",
      "name": "Robert E. Sherwood"
    },
    {
      "id": "nm0437969",
      "name": "MacKinlay Kantor"
    }
  ],
  "stars": "Myrna Loy, Dana Andrews, Fredric March",
  "starList": [
    {
      "id": "nm0001485",
      "name": "Myrna Loy"
    },
    {
      "id": "nm0000763",
      "name": "Dana Andrews"
    },
    {
      "id": "nm0545298",
      "name": "Fredric March"
    }
  ],
  "actorList": [
    {
      "id": "nm0001485",
      "image": "https://m.media-amazon.com/images/M/MV5BMjAwMzU0NjY4NF5BMl5BanBnXkFtZTYwNDE3NjQ2._V1_Ratio1.0000_AL_.jpg",
      "name": "Myrna Loy",
      "asCharacter": "Milly Stephenson"
    },
    {
      "id": "nm0000763",
      "image": "https://m.media-amazon.com/images/M/MV5BNjQ3ODQzNjQ1MV5BMl5BanBnXkFtZTYwMjExMTM2._V1_Ratio1.0000_AL_.jpg",
      "name": "Dana Andrews",
      "asCharacter": "Fred Derry"
    },
    {
      "id": "nm0545298",
      "image": "https://m.media-amazon.com/images/M/MV5BNTI3MDEyMzg2OF5BMl5BanBnXkFtZTYwNzA2MjI2._V1_Ratio1.0000_AL_.jpg",
      "name": "Fredric March",
      "asCharacter": "Al Stephenson"
    },
    {
      "id": "nm0942863",
      "image": "https://m.media-amazon.com/images/M/MV5BMjA5NDk5MDU1Ml5BMl5BanBnXkFtZTYwMjg2MjI2._V1_Ratio1.0000_AL_.jpg",
      "name": "Teresa Wright",
      "asCharacter": "Peggy Stephenson"
    },
    {
      "id": "nm0562920",
      "image": "https://m.media-amazon.com/images/M/MV5BZjVmMzlkNzYtMmVlYi00YzkzLTg1MWMtNjY3NzA4Yjc0NjExXkEyXkFqcGdeQXVyMDc2NTEzMw@@._V1_Ratio1.0000_AL_.jpg",
      "name": "Virginia Mayo",
      "asCharacter": "Marie Derry"
    },
    {
      "id": "nm0640732",
      "image": "https://m.media-amazon.com/images/M/MV5BMTgyNzU4Mzg5N15BMl5BanBnXkFtZTcwNjkzODMxOA@@._V1_Ratio1.0000_AL_.jpg",
      "name": "Cathy O'Donnell",
      "asCharacter": "Wilma Cameron"
    },
    {
      "id": "nm0005994",
      "image": "https://m.media-amazon.com/images/M/MV5BMTU5MTQzMzY5MF5BMl5BanBnXkFtZTcwNjkyNTcxOA@@._V1_Ratio1.0000_AL_.jpg",
      "name": "Hoagy Carmichael",
      "asCharacter": "Butch Engle"
    },
    {
      "id": "nm0751174",
      "image": "https://m.media-amazon.com/images/M/MV5BNTU3MDYwODgyNl5BMl5BanBnXkFtZTcwNTU4OTQwNw@@._V1_Ratio1.0000_AL_.jpg",
      "name": "Harold Russell",
      "asCharacter": "Homer Parrish"
    },
    {
      "id": "nm0313438",
      "image": "https://m.media-amazon.com/images/M/MV5BMjE0MjkwNDk0OV5BMl5BanBnXkFtZTgwODU4NDE2MDE@._V1_Ratio1.0000_AL_.jpg",
      "name": "Gladys George",
      "asCharacter": "Hortense Derry"
    },
    {
      "id": "nm0092129",
      "image": "https://m.media-amazon.com/images/M/MV5BNjE2OTUyMTAtMjZmYy00NjBmLWJlMGYtNTM2N2U3MzYzMzA4L2ltYWdlL2ltYWdlXkEyXkFqcGdeQXVyMzI5NDcxNzI@._V1_Ratio1.0000_AL_.jpg",
      "name": "Roman Bohnen",
      "asCharacter": "Pat Derry"
    },
    {
      "id": "nm0172615",
      "image": "https://m.media-amazon.com/images/M/MV5BMjIzNTU4NzUxMV5BMl5BanBnXkFtZTcwMDQyMzYwOA@@._V1_Ratio1.0000_AL_.jpg",
      "name": "Ray Collins",
      "asCharacter": "Mr. Milton"
    },
    {
      "id": "nm0326809",
      "image": "https://m.media-amazon.com/images/M/MV5BYmQ5NGY3Y2YtMTZlMy00ZGFmLTk5YWMtODg0NDZkODExMzFkXkEyXkFqcGdeQXVyMzI5NDcxNzI@._V1_Ratio1.0000_AL_.jpg",
      "name": "Minna Gombell",
      "asCharacter": "Mrs. Parrish"
    },
    {
      "id": "nm0050019",
      "image": "https://m.media-amazon.com/images/M/MV5BMjEzNzQ3NDAzMF5BMl5BanBnXkFtZTgwMzMwODg3MjE@._V1_Ratio1.3429_AL_.jpg",
      "name": "Walter Baldwin",
      "asCharacter": "Mr. Parrish"
    },
    {
      "id": "nm0168215",
      "image": "https://m.media-amazon.com/images/M/MV5BZGZmZGEwNTItZGJhYy00OTgyLWJiMzYtYzk1OGI3NGZlMzFmXkEyXkFqcGdeQXVyMDUyOTUyNQ@@._V1_Ratio1.0000_AL_.jpg",
      "name": "Steve Cochran",
      "asCharacter": "Cliff"
    },
    {
      "id": "nm0010928",
      "image": "https://m.media-amazon.com/images/M/MV5BNGZmMjQ0Y2EtNTY0Mi00MzY3LWJhMjYtYWRhODJkZGUxNzdhXkEyXkFqcGdeQXVyMzI5NDcxNzI@._V1_Ratio1.0000_AL_.jpg",
      "name": "Dorothy Adams",
      "asCharacter": "Mrs. Cameron"
    },
    {
      "id": "nm0065975",
      "image": "https://m.media-amazon.com/images/M/MV5BNjU1NDI4NzgwMl5BMl5BanBnXkFtZTcwNjY5MjYwOA@@._V1_Ratio1.0000_AL_.jpg",
      "name": "Don Beddoe",
      "asCharacter": "Mr. Cameron"
    },
    {
      "id": "nm0007408",
      "image": "https://imdb-api.com/images/original/nopicture.jpg",
      "name": "Marlene Aames",
      "asCharacter": "Luella Parrish"
    },
    {
      "id": "nm0357111",
      "image": "https://m.media-amazon.com/images/M/MV5BNjdiNmQ1NjYtNDNhZi00MmIwLWE5YzctMzYyYmQ0OGQ2ZDg5XkEyXkFqcGdeQXVyMTcyODY2NDQ@._V1_Ratio1.0000_AL_.jpg",
      "name": "Charles Halton",
      "asCharacter": "Prew"
    }
  ],
  "fullCast": null,
  "genres": "Drama, Romance, War",
  "genreList": [
    {
      "key": "Drama",
      "value": "Drama"
    },
    {
      "key": "Romance",
      "value": "Romance"
    },
    {
      "key": "War",
      "value": "War"
    }
  ],
  "companies": "The Samuel Goldwyn Company",
  "companyList": [
    {
      "id": "co0016710",
      "name": "The Samuel Goldwyn Company"
    }
  ],
  "countries": "USA",
  "countryList": [
    {
      "key": "USA",
      "value": "USA"
    }
  ],
  "languages": "English",
  "languageList": [
    {
      "key": "English",
      "value": "English"
    }
  ],
  "contentRating": "Approved",
  "imDbRating": "8.1",
  "imDbRatingVotes": "67166",
  "metacriticRating": "93",
  "ratings": null,
  "wikipedia": null,
  "posters": null,
  "images": null,
  "trailer": null,
  "boxOffice": {
    "budget": "$2,100,000 (estimated)",
    "openingWeekendUSA": "",
    "grossUSA": "$23,650,000",
    "cumulativeWorldwideGross": "$23,661,347"
  },
  "tagline": null,
  "keywords": "readjusting to civilian life,world war two veteran,banker,speech,bombardier",
  "keywordList": [
    "readjusting to civilian life",
    "world war two veteran",
    "banker",
    "speech",
    "bombardier"
  ],
  "similars": [
    {
      "id": "tt0035446",
      "title": "To Be or Not to Be",
      "image": "https://m.media-amazon.com/images/M/MV5BMGY3ZDgzY2MtNTllNi00ZWI1LTk1NTUtNWEzN2Q4YTA1ZGZiXkEyXkFqcGdeQXVyNzI1NzMxNzM@._V1_Ratio0.6957_AL_.jpg",
      "imDbRating": "8.2"
    },
    {
      "id": "tt0032551",
      "title": "The Grapes of Wrath",
      "image": "https://m.media-amazon.com/images/M/MV5BNzJiOGI2MjctYjUyMS00ZjkzLWE2ZmUtOTg4NTZkOTNhZDc1L2ltYWdlXkEyXkFqcGdeQXVyNjc1NTYyMjg@._V1_Ratio0.6763_AL_.jpg",
      "imDbRating": "8.1"
    },
    {
      "id": "tt0025316",
      "title": "It Happened One Night",
      "image": "https://m.media-amazon.com/images/M/MV5BYzJmMWE5NjAtNWMyZS00NmFiLWIwMDgtZDE2NzczYWFhNzIzXkEyXkFqcGdeQXVyNjc1NTYyMjg@._V1_Ratio0.6763_AL_.jpg",
      "imDbRating": "8.1"
    },
    {
      "id": "tt0031679",
      "title": "Mr. Smith Goes to Washington",
      "image": "https://m.media-amazon.com/images/M/MV5BZTYwYjYxYzgtMDE1Ni00NzU4LWJlMTEtODQ5YmJmMGJhZjI5L2ltYWdlXkEyXkFqcGdeQXVyMDI2NDg0NQ@@._V1_Ratio0.6763_AL_.jpg",
      "imDbRating": "8.1"
    },
    {
      "id": "tt0032976",
      "title": "Rebecca",
      "image": "https://m.media-amazon.com/images/M/MV5BYTcxYWExOTMtMWFmYy00ZjgzLWI0YjktNWEzYzJkZTg0NDdmL2ltYWdlXkEyXkFqcGdeQXVyNjc1NTYyMjg@._V1_Ratio0.6957_AL_.jpg",
      "imDbRating": "8.1"
    },
    {
      "id": "tt0042192",
      "title": "All About Eve",
      "image": "https://m.media-amazon.com/images/M/MV5BMTY2MTAzODI5NV5BMl5BanBnXkFtZTgwMjM4NzQ0MjE@._V1_Ratio0.6763_AL_.jpg",
      "imDbRating": "8.2"
    },
    {
      "id": "tt0040897",
      "title": "The Treasure of the Sierra Madre",
      "image": "https://m.media-amazon.com/images/M/MV5BOTJlZWMxYzEtMjlkMS00ODE0LThlM2ItMDI3NGQ2YjhmMzkxXkEyXkFqcGdeQXVyMDI2NDg0NQ@@._V1_Ratio0.6763_AL_.jpg",
      "imDbRating": "8.2"
    },
    {
      "id": "tt0058946",
      "title": "The Battle of Algiers",
      "image": "https://m.media-amazon.com/images/M/MV5BN2M4YTA4ZTEtN2EyNy00YTlmLWE4YzYtYjYyYjRkMWM4ZDM0XkEyXkFqcGdeQXVyMjUzOTY1NTc@._V1_Ratio0.6763_AL_.jpg",
      "imDbRating": "8.1"
    },
    {
      "id": "tt0035093",
      "title": "Mrs. Miniver",
      "image": "https://m.media-amazon.com/images/M/MV5BY2UxNjcwYmQtODc1NC00ZjQ1LTk4NDctZTE0NjhlMjNlOTEyXkEyXkFqcGdeQXVyNjc1NTYyMjg@._V1_Ratio0.6860_AL_.jpg",
      "imDbRating": "7.6"
    },
    {
      "id": "tt0046268",
      "title": "The Wages of Fear",
      "image": "https://m.media-amazon.com/images/M/MV5BZDdkNzMwZmUtY2Q5MS00ZmM2LWJhYjItYTBjMWY0MGM4MDRjXkEyXkFqcGdeQXVyNTA4NzY1MzY@._V1_Ratio0.6860_AL_.jpg",
      "imDbRating": "8.2"
    },
    {
      "id": "tt0047296",
      "title": "On the Waterfront",
      "image": "https://m.media-amazon.com/images/M/MV5BY2I0MWFiZDMtNWQyYy00Njk5LTk3MDktZjZjNTNmZmVkYjkxXkEyXkFqcGdeQXVyNjc1NTYyMjg@._V1_Ratio0.6763_AL_.jpg",
      "imDbRating": "8.1"
    },
    {
      "id": "tt0037884",
      "title": "The Lost Weekend",
      "image": "https://m.media-amazon.com/images/M/MV5BMTk4NDQ0NjgyNF5BMl5BanBnXkFtZTgwMTE3NTkxMTE@._V1_Ratio0.6763_AL_.jpg",
      "imDbRating": "7.9"
    }
  ],
  "tvSeriesInfo": null,
  "tvEpisodeInfo": null,
  "errorMessage": ""
}